pylint_behave/__init__.py
pylint_behave/__pkginfo__.py
pylint_behave/augmentations.py
pylint_behave/compat.py
pylint_behave/plugin.py
pylint_behave/version.py
pylint_behave/checkers/__init__.py
pylint_behave/checkers/behave_installed.py
pylint_behave/tests/test.py
pylint_behave/tests/cases/basic_class.py
pylint_behave/tests/cases/behave_steps.py
pylint_behave/tests/cases/behave_steps_with_errors.py
pylint_behave-1.0.2.dist-info/LICENSE
pylint_behave-1.0.2.dist-info/METADATA
pylint_behave-1.0.2.dist-info/WHEEL
pylint_behave-1.0.2.dist-info/top_level.txt
pylint_behave-1.0.2.dist-info/RECORD
