Metadata-Version: 2.1
Name: pylint-behave
Version: 1.0.2
Summary: Pylint plugin to help Pylint understand the Behave projects
Home-page: https://github.com/eccanto/pylint-behave
Author: Erik Ccanto
Author-email: ccanto.erik@gmail.com
License: MIT
Keywords: pylint,behave,plugin
Classifier: Environment :: Console
Classifier: Intended Audience :: Developers
Classifier: Operating System :: Unix
Classifier: Topic :: Software Development :: Quality Assurance
Classifier: Programming Language :: Python :: 3.7
Classifier: Programming Language :: Python :: 3.8
Classifier: Programming Language :: Python :: 3.9
Classifier: Programming Language :: Python :: 3.10
Classifier: Programming Language :: Python :: 3.11
Classifier: Programming Language :: Python :: 3.12
Requires-Python: >=3.7.15
License-File: LICENSE
Requires-Dist: behave (>=1.2.5)
Requires-Dist: pylint (>=2.0)
Requires-Dist: pylint-plugin-utils (>=0.5)
